<?xml version="1.0"?>
<libraries>
  <library>
    <location>cli</location>
    <name>Server Cli scripts</name>
    <license>GPL</license>
    <version>3.0</version>
    <licenseversion>3=GPL V3</licenseversion>
  </library>
  <library>
    <location>pro</location>
    <name>Pro zone compiled scripts</name>
    <license>APL</license>
    <version></version>
    <licenseversion></licenseversion>
  </library>
  <library>
    <location>plugins</location>
    <name>Metadata subplugins</name>
    <license>GPL</license>
    <version>3</version>
    <licenseversion>GPL V3</licenseversion>
  </library>
</libraries>
